{
  "summary": {
    "step": "72",
    "name": "Интеграция за пълно обновяване на статистическата верига",
    "mode": "run",
    "include_core": false,
    "steps_planned": 20,
    "steps_reported": 20,
    "all_scripts_present": true,
    "all_outputs_present": true,
    "run_pipeline": true,
    "run_ok": true,
    "stopped_at": "",
    "weighted_steps": [
      "61",
      "62",
      "63",
      "65",
      "66",
      "67",
      "68",
      "69",
      "70",
      "71",
      "73",
      "75",
      "76",
      "77",
      "78",
      "79",
      "80",
      "81",
      "82",
      "74"
    ],
    "core_steps_included": [],
    "generated_at": "2026-06-28T16:43:17+00:00",
    "generated_reports": [
      "reports/v72_pipeline_refresh_summary.json",
      "reports/v72_pipeline_refresh_summary.md",
      "reports/v72_pipeline_refresh_plan.csv",
      "models/v72/v72_pipeline_refresh_model.json"
    ],
    "safe_note": "Тази верига обновява само статистически файлове. Не е предсказание и не е гаранция за печалба."
  },
  "steps": [
    {
      "step": "61",
      "name": "Анализ на нов тираж",
      "script": "scripts/v61_build_draw_result_analyzer.py",
      "script_exists": true,
      "outputs": "models/v61; reports/v61_draw_result_analyzer_summary.json",
      "outputs_ok": true,
      "latest_output_mtime": "2026-06-28T19:40:35",
      "run_status": "OK",
      "run_ok": true,
      "run_output_tail": "V61_DRAW_RESULT_ANALYZER_OK\nTOTAL_DRAWS 10059\nLATEST_DATE 2026-06-25\nLATEST_DRAW 49\nLATEST_NUMBERS 5, 11, 44, 46, 47, 48\nBEST_SIGNAL_HITS 2\nSIGNALS_CHECKED 27"
    },
    {
      "step": "62",
      "name": "История на моделите",
      "script": "scripts/v62_build_model_performance_tracker.py",
      "script_exists": true,
      "outputs": "models/v62; reports/v62_model_performance_summary.json",
      "outputs_ok": true,
      "latest_output_mtime": "2026-06-28T19:40:36",
      "run_status": "OK",
      "run_ok": true,
      "run_output_tail": "STEP62_BUILD_OK\nTOTAL_DRAWS 10059\nLATEST_DRAW {'date': '2026-06-25', 'year': '2026', 'draw_number': '49', 'draw_position': '1', 'numbers': [5, 11, 44, 46, 47, 48]}\nMODELS_EVALUATED 10\nBEST_HITS 2"
    },
    {
      "step": "63",
      "name": "Надеждност на моделите",
      "script": "scripts/v63_build_model_reliability_dashboard.py",
      "script_exists": true,
      "outputs": "models/v63; reports/v63_model_reliability_summary.json",
      "outputs_ok": true,
      "latest_output_mtime": "2026-06-28T19:40:36",
      "run_status": "OK",
      "run_ok": true,
      "run_output_tail": "STEP63_BUILD_OK\nHISTORY_ROWS 20\nTRACKED_DRAWS 2\nMODELS_RANKED 10\nBEST_MODEL v44.1\nBEST_SCORE 65.0"
    },
    {
      "step": "65",
      "name": "Умно тегло на моделите",
      "script": "scripts/v65_build_model_weighting_center.py",
      "script_exists": true,
      "outputs": "models/v65; reports/v65_model_weighting_summary.json",
      "outputs_ok": true,
      "latest_output_mtime": "2026-06-28T19:40:36",
      "run_status": "OK",
      "run_ok": true,
      "run_output_tail": "STEP65_BUILD_OK\nMODELS_WEIGHTED 10\nTOP_MODEL v44.1\nTOP_WEIGHT 20.17"
    },
    {
      "step": "66",
      "name": "Претеглен ансамбъл анализ",
      "script": "scripts/v66_build_weighted_smart_ensemble.py",
      "script_exists": true,
      "outputs": "models/v66; reports/v66_weighted_smart_ensemble_summary.json",
      "outputs_ok": true,
      "latest_output_mtime": "2026-06-28T19:40:37",
      "run_status": "OK",
      "run_ok": true,
      "run_output_tail": "STEP66_BUILD_OK\nSOURCES_USED 8\nNUMBERS_SCORED 49\nTOP_NUMBER 1\nTOP_SCORE 100.0"
    },
    {
      "step": "67",
      "name": "Умен генератор с тегла",
      "script": "scripts/v67_build_weighted_ticket_builder.py",
      "script_exists": true,
      "outputs": "models/v67; reports/v67_weighted_ticket_builder_summary.json",
      "outputs_ok": true,
      "latest_output_mtime": "2026-06-28T19:42:22",
      "run_status": "OK",
      "run_ok": true,
      "run_output_tail": "STEP67_BUILD_OK\nTICKETS_GENERATED 8\nTOP_TICKET_ID 2\nTOP_AVG_SCORE 81.032"
    },
    {
      "step": "68",
      "name": "Умен оптимизатор на портфейл",
      "script": "scripts/v68_build_weighted_portfolio_optimizer.py",
      "script_exists": true,
      "outputs": "models/v68; reports/v68_weighted_portfolio_summary.json",
      "outputs_ok": true,
      "latest_output_mtime": "2026-06-28T19:42:23",
      "run_status": "OK",
      "run_ok": true,
      "run_output_tail": "STEP68_BUILD_OK\nTICKETS_ANALYZED 8\nUNIQUE_NUMBERS_COVERED 19\nPORTFOLIO_SCORE 66.619\nPORTFOLIO_STATUS"
    },
    {
      "step": "69",
      "name": "Подобряване на портфолио",
      "script": "scripts/v69_build_portfolio_improvement_suggestions.py",
      "script_exists": true,
      "outputs": "models/v69; reports/v69_portfolio_improvement_summary.json",
      "outputs_ok": true,
      "latest_output_mtime": "2026-06-28T19:42:23",
      "run_status": "OK",
      "run_ok": true,
      "run_output_tail": "STEP69_BUILD_OK\nSUGGESTIONS_GENERATED 48\nCANDIDATE_CHANGES 1\nBASELINE_SCORE 66.619\nCANDIDATE_SCORE 69.588"
    },
    {
      "step": "70",
      "name": "Приложен подобрен портфейл",
      "script": "scripts/v70_build_applied_candidate_portfolio.py",
      "script_exists": true,
      "outputs": "models/v70; reports/v70_applied_candidate_portfolio_summary.json",
      "outputs_ok": true,
      "latest_output_mtime": "2026-06-28T19:42:23",
      "run_status": "OK",
      "run_ok": true,
      "run_output_tail": "STEP70_BUILD_OK\nAPPLIED_TICKETS 8\nAPPLIED_CHANGES 1\nORIGINAL_SCORE 66.619\nAPPLIED_SCORE 69.588"
    },
    {
      "step": "71",
      "name": "Пакет за игра",
      "script": "scripts/v71_build_ticket_pack_export.py",
      "script_exists": true,
      "outputs": "models/v71; reports/v71_ticket_pack_summary.json",
      "outputs_ok": true,
      "latest_output_mtime": "2026-06-28T19:42:23",
      "run_status": "OK",
      "run_ok": true,
      "run_output_tail": "STEP71_BUILD_OK\nTICKETS_EXPORTED 8\nCHANGES_INCLUDED 1\nAPPLIED_SCORE 69.588"
    },
    {
      "step": "73",
      "name": "Представяне на пакета",
      "script": "scripts/v73_build_ticket_pack_performance_tracker.py",
      "script_exists": true,
      "outputs": "models/v73; reports/v73_ticket_pack_performance_summary.json",
      "outputs_ok": true,
      "latest_output_mtime": "2026-06-28T19:42:23",
      "run_status": "OK",
      "run_ok": true,
      "run_output_tail": "STEP73_BUILD_OK\nACTIVE_PACK_TICKETS 8\nHISTORY_ROWS 1\nSTATUS"
    },
    {
      "step": "75",
      "name": "Невронен мета обучител",
      "script": "scripts/v75_build_neural_meta_learner.py",
      "script_exists": true,
      "outputs": "models/v75; reports/v75_neural_meta_learner_summary.json; reports/v75_neural_candidate_tickets.csv",
      "outputs_ok": true,
      "latest_output_mtime": "2026-06-28T19:42:55",
      "run_status": "OK",
      "run_ok": true,
      "run_output_tail": "STEP75_BUILD_OK\nSTATUS\nVALID_DRAWS 10059\nAVG_HITS_TOP6 0.748\nMAX_HITS_TOP6 4\nTOP_NUMBERS 21,34,45,40,2,25"
    },
    {
      "step": "76",
      "name": "Обяснимост и валидация",
      "script": "scripts/v76_build_explainability_validation_center.py",
      "script_exists": true,
      "outputs": "models/v76; reports/v76_explainability_validation_summary.json",
      "outputs_ok": true,
      "latest_output_mtime": "2026-06-28T19:42:56",
      "run_status": "OK",
      "run_ok": true,
      "run_output_tail": "STEP76_BUILD_OK\nSTATUS OK\nVALID_DRAWS 10060\nNUMBERS_EXPLAINED 49\nTICKETS_VALIDATED 8\nWARNING_ITEMS 10"
    },
    {
      "step": "77",
      "name": "Решение и препоръка",
      "script": "scripts/v77_build_decision_recommendation_center.py",
      "script_exists": true,
      "outputs": "models/v77; reports/v77_decision_recommendation_summary.json",
      "outputs_ok": true,
      "latest_output_mtime": "2026-06-28T19:42:56",
      "run_status": "OK",
      "run_ok": true,
      "run_output_tail": "STEP77_BUILD_OK\nSTATUS OK\nVALID_DRAWS 10060\nRECOMMENDATIONS 8\nBEST_TICKET 5\nBEST_SCORE 62.744"
    },
    {
      "step": "78",
      "name": "Финален план",
      "script": "scripts/v78_build_final_play_plan_center.py",
      "script_exists": true,
      "outputs": "models/v78; reports/v78_final_play_plan_summary.json",
      "outputs_ok": true,
      "latest_output_mtime": "2026-06-28T19:42:56",
      "run_status": "OK",
      "run_ok": true,
      "run_output_tail": "STEP78_BUILD_OK\nSTATUS OK\nVALID_DRAWS 10060\nCANDIDATES 8\nACTIVE_TICKETS 3\nRESERVE_TICKETS 3\nBEST_TICKET 5"
    },
    {
      "step": "79",
      "name": "Експорт и изпълнение",
      "script": "scripts/v79_build_ticket_pack_export_center.py",
      "script_exists": true,
      "outputs": "models/v79; reports/v79_ticket_pack_export_summary.json",
      "outputs_ok": true,
      "latest_output_mtime": "2026-06-28T19:42:56",
      "run_status": "OK",
      "run_ok": true,
      "run_output_tail": "STEP79_BUILD_OK\nSTATUS OK\nVALID_DRAWS 10060\nCANDIDATES 8\nPLAY_TICKETS 3\nRESERVE_TICKETS 3\nBEST_TICKET 5"
    },
    {
      "step": "80",
      "name": "Финален системен одит",
      "script": "scripts/v80_build_final_system_audit_center.py",
      "script_exists": true,
      "outputs": "models/v80; reports/v80_final_system_audit_summary.json",
      "outputs_ok": true,
      "latest_output_mtime": "2026-06-28T19:43:17",
      "run_status": "OK",
      "run_ok": true,
      "run_output_tail": "STEP80_BUILD_OK\nSTATUS\nDATASETS_CHECKED 3\nARTIFACTS_CHECKED 27\nQUALITY_CHECKS 33\nSYNC_PLANS_CHECKED 3\nISSUES_FOUND 4"
    },
    {
      "step": "81",
      "name": "Финален UX контрол",
      "script": "scripts/v81_build_final_ux_navigation_center.py",
      "script_exists": true,
      "outputs": "models/v81; reports/v81_final_ux_navigation_summary.json",
      "outputs_ok": true,
      "latest_output_mtime": "2026-06-28T19:43:17",
      "run_status": "OK",
      "run_ok": true,
      "run_output_tail": "STEP81_BUILD_OK\nSTATUS\nGROUPS_CHECKED 7\nNAVIGATION_PAGES 80\nDUPLICATE_PAGES 0\nSYSTEM_ORDER_OK True\nISSUES_FOUND 1"
    },
    {
      "step": "82",
      "name": "Финален пакет за предаване",
      "script": "scripts/v82_build_final_release_package_center.py",
      "script_exists": true,
      "outputs": "models/v82; reports/v82_final_release_summary.json",
      "outputs_ok": true,
      "latest_output_mtime": "2026-06-28T19:43:17",
      "run_status": "OK",
      "run_ok": true,
      "run_output_tail": "STEP82_BUILD_OK\nSTATUS\nREQUIRED_FILES_CHECKED 22\nDATASETS_CHECKED 3\nMANIFEST_FILES 1156\nUNWANTED_RELEASE_FILES 0\nISSUES_FOUND 5"
    },
    {
      "step": "74",
      "name": "Контрол на синхрона между моделите",
      "script": "scripts/v74_build_model_dependency_sync_center.py",
      "script_exists": true,
      "outputs": "models/v74; reports/v74_model_dependency_summary.json; models/model_registry.json",
      "outputs_ok": true,
      "latest_output_mtime": "2026-06-28T19:43:17",
      "run_status": "OK",
      "run_ok": true,
      "run_output_tail": "STEP74_BUILD_OK\nSTATUS\nMODELS_CHECKED 32\nSYNCED_MODELS 9\nSTALE_MODELS 23\nMISSING_MODELS 0"
    }
  ]
}