{
  "status": "v45_prediction_engine_pro_scores_ready",
  "created_at_utc": "2026-06-28T16:43:47.159330+00:00",
  "dataset": {
    "total_events": 10060,
    "year_min": 1958,
    "year_max": 2026,
    "drawing_no_counts": {
      "1": 5178,
      "2": 3587,
      "3": 1280,
      "4": 15
    },
    "duplicate_keys": 0,
    "invalid_rows": 0
  },
  "latest_seen_event": {
    "year": 2026,
    "draw_number": 50,
    "drawing_no": 1,
    "date": "2026-06-28",
    "numbers": [
      2,
      4,
      17,
      33,
      35,
      38
    ]
  },
  "next_event_assumption": {
    "year": 2026,
    "draw_number": 51,
    "drawing_no": 1
  },
  "uses_bonus_number": false,
  "numbers": [
    {
      "number": 48,
      "rank": 1,
      "current_gap": 2,
      "average_gap": 7.916469661150512,
      "median_gap": 6.0,
      "total_hits": 1270,
      "prior_frequency": 0.12624254473161034,
      "rolling_250_frequency": 0.14,
      "gap_rhythm_score": 0.1156803524378619,
      "sgd_log_probability": 0.5204359578721756,
      "gaussian_nb_probability": 0.16409669432400797,
      "pro_ensemble_score": 0.7624489795918367
    },
    {
      "number": 44,
      "rank": 2,
      "current_gap": 2,
      "average_gap": 7.785437645236251,
      "median_gap": 5.0,
      "total_hits": 1292,
      "prior_frequency": 0.12842942345924455,
      "rolling_250_frequency": 0.104,
      "gap_rhythm_score": 0.11979987199128876,
      "sgd_log_probability": 0.519791429525917,
      "gaussian_nb_probability": 0.19698302158023023,
      "pro_ensemble_score": 0.7273469387755103
    },
    {
      "number": 43,
      "rank": 3,
      "current_gap": 7,
      "average_gap": 8.212940212940213,
      "median_gap": 6.0,
      "total_hits": 1222,
      "prior_frequency": 0.12147117296222663,
      "rolling_250_frequency": 0.144,
      "gap_rhythm_score": 0.13803512830740594,
      "sgd_log_probability": 0.5108703280634979,
      "gaussian_nb_probability": 0.16204471736573517,
      "pro_ensemble_score": 0.7220408163265307
    },
    {
      "number": 17,
      "rank": 4,
      "current_gap": 1,
      "average_gap": 7.927387529597475,
      "median_gap": 6.0,
      "total_hits": 1268,
      "prior_frequency": 0.12604373757455267,
      "rolling_250_frequency": 0.132,
      "gap_rhythm_score": 0.10658141330743828,
      "sgd_log_probability": 0.508232871185505,
      "gaussian_nb_probability": 0.16333585113271512,
      "pro_ensemble_score": 0.686530612244898
    },
    {
      "number": 22,
      "rank": 5,
      "current_gap": 4,
      "average_gap": 8.048038430744596,
      "median_gap": 6.0,
      "total_hits": 1250,
      "prior_frequency": 0.1242544731610338,
      "rolling_250_frequency": 0.152,
      "gap_rhythm_score": 0.12058045549319167,
      "sgd_log_probability": 0.5043933126304013,
      "gaussian_nb_probability": 0.15973430991602833,
      "pro_ensemble_score": 0.6840816326530612
    },
    {
      "number": 49,
      "rank": 6,
      "current_gap": 8,
      "average_gap": 7.894736842105263,
      "median_gap": 6.0,
      "total_hits": 1274,
      "prior_frequency": 0.12664015904572565,
      "rolling_250_frequency": 0.124,
      "gap_rhythm_score": 0.19653078908148247,
      "sgd_log_probability": 0.5041446962526244,
      "gaussian_nb_probability": 0.15753922213070778,
      "pro_ensemble_score": 0.6804081632653061
    },
    {
      "number": 11,
      "rank": 7,
      "current_gap": 2,
      "average_gap": 7.8931657501963866,
      "median_gap": 6.0,
      "total_hits": 1274,
      "prior_frequency": 0.12664015904572565,
      "rolling_250_frequency": 0.128,
      "gap_rhythm_score": 0.12671300776513428,
      "sgd_log_probability": 0.5034967988783641,
      "gaussian_nb_probability": 0.16166744432217697,
      "pro_ensemble_score": 0.6702040816326531
    },
    {
      "number": 29,
      "rank": 8,
      "current_gap": 4,
      "average_gap": 8.00796812749004,
      "median_gap": 6.0,
      "total_hits": 1256,
      "prior_frequency": 0.12485089463220676,
      "rolling_250_frequency": 0.12,
      "gap_rhythm_score": 0.11698963620611252,
      "sgd_log_probability": 0.5103506919407071,
      "gaussian_nb_probability": 0.16311852076154246,
      "pro_ensemble_score": 0.6636734693877552
    },
    {
      "number": 37,
      "rank": 9,
      "current_gap": 6,
      "average_gap": 7.88078431372549,
      "median_gap": 6.0,
      "total_hits": 1276,
      "prior_frequency": 0.1268389662027833,
      "rolling_250_frequency": 0.168,
      "gap_rhythm_score": 0.18745657760626144,
      "sgd_log_probability": 0.5001835715599595,
      "gaussian_nb_probability": 0.14718107158654992,
      "pro_ensemble_score": 0.6526530612244898
    },
    {
      "number": 42,
      "rank": 10,
      "current_gap": 3,
      "average_gap": 8.14331983805668,
      "median_gap": 6.0,
      "total_hits": 1236,
      "prior_frequency": 0.12286282306163022,
      "rolling_250_frequency": 0.14,
      "gap_rhythm_score": 0.12768861830555492,
      "sgd_log_probability": 0.5211553472767045,
      "gaussian_nb_probability": 0.14729493343728278,
      "pro_ensemble_score": 0.646938775510204
    },
    {
      "number": 46,
      "rank": 11,
      "current_gap": 2,
      "average_gap": 8.071428571428571,
      "median_gap": 6.0,
      "total_hits": 1247,
      "prior_frequency": 0.12395626242544731,
      "rolling_250_frequency": 0.116,
      "gap_rhythm_score": 0.09349788378991303,
      "sgd_log_probability": 0.5204764423620033,
      "gaussian_nb_probability": 0.16584177601505073,
      "pro_ensemble_score": 0.6412244897959184
    },
    {
      "number": 35,
      "rank": 12,
      "current_gap": 1,
      "average_gap": 8.079646017699115,
      "median_gap": 6.0,
      "total_hits": 1244,
      "prior_frequency": 0.12365805168986084,
      "rolling_250_frequency": 0.148,
      "gap_rhythm_score": 0.0826578016671688,
      "sgd_log_probability": 0.5258913166707824,
      "gaussian_nb_probability": 0.1582434462285809,
      "pro_ensemble_score": 0.6326530612244898
    },
    {
      "number": 28,
      "rank": 13,
      "current_gap": 4,
      "average_gap": 8.044,
      "median_gap": 6.0,
      "total_hits": 1251,
      "prior_frequency": 0.12435387673956262,
      "rolling_250_frequency": 0.116,
      "gap_rhythm_score": 0.11938139352200683,
      "sgd_log_probability": 0.5016675105063141,
      "gaussian_nb_probability": 0.16352043881995526,
      "pro_ensemble_score": 0.6236734693877551
    },
    {
      "number": 6,
      "rank": 14,
      "current_gap": 3,
      "average_gap": 7.90566037735849,
      "median_gap": 6.0,
      "total_hits": 1273,
      "prior_frequency": 0.1265407554671968,
      "rolling_250_frequency": 0.112,
      "gap_rhythm_score": 0.12160439410462269,
      "sgd_log_probability": 0.5010067433998967,
      "gaussian_nb_probability": 0.1630604696555737,
      "pro_ensemble_score": 0.6212244897959184
    },
    {
      "number": 39,
      "rank": 15,
      "current_gap": 7,
      "average_gap": 8.291149710504548,
      "median_gap": 6.0,
      "total_hits": 1210,
      "prior_frequency": 0.12027833001988071,
      "rolling_250_frequency": 0.124,
      "gap_rhythm_score": 0.13758137802607076,
      "sgd_log_probability": 0.5046890668402512,
      "gaussian_nb_probability": 0.16191681950053163,
      "pro_ensemble_score": 0.6146938775510203
    },
    {
      "number": 33,
      "rank": 16,
      "current_gap": 1,
      "average_gap": 8.193969030154848,
      "median_gap": 6.0,
      "total_hits": 1228,
      "prior_frequency": 0.1220675944333996,
      "rolling_250_frequency": 0.132,
      "gap_rhythm_score": 0.07296313639679067,
      "sgd_log_probability": 0.5120613174474529,
      "gaussian_nb_probability": 0.16240417262371168,
      "pro_ensemble_score": 0.5889795918367347
    },
    {
      "number": 30,
      "rank": 17,
      "current_gap": 7,
      "average_gap": 8.066666666666666,
      "median_gap": 6.0,
      "total_hits": 1246,
      "prior_frequency": 0.1238568588469185,
      "rolling_250_frequency": 0.124,
      "gap_rhythm_score": 0.1507137547529131,
      "sgd_log_probability": 0.4930784155551258,
      "gaussian_nb_probability": 0.16297058704808004,
      "pro_ensemble_score": 0.586530612244898
    },
    {
      "number": 38,
      "rank": 18,
      "current_gap": 1,
      "average_gap": 8.17059301380991,
      "median_gap": 6.0,
      "total_hits": 1232,
      "prior_frequency": 0.12246520874751492,
      "rolling_250_frequency": 0.164,
      "gap_rhythm_score": 0.10383767635288664,
      "sgd_log_probability": 0.5182725690106034,
      "gaussian_nb_probability": 0.14694532824648748,
      "pro_ensemble_score": 0.5742857142857143
    },
    {
      "number": 26,
      "rank": 19,
      "current_gap": 4,
      "average_gap": 8.254515599343186,
      "median_gap": 6.0,
      "total_hits": 1219,
      "prior_frequency": 0.12117296222664016,
      "rolling_250_frequency": 0.128,
      "gap_rhythm_score": 0.11369499635302699,
      "sgd_log_probability": 0.5059795157699288,
      "gaussian_nb_probability": 0.16067920092273733,
      "pro_ensemble_score": 0.5648979591836735
    },
    {
      "number": 8,
      "rank": 20,
      "current_gap": 5,
      "average_gap": 8.076305220883533,
      "median_gap": 6.0,
      "total_hits": 1246,
      "prior_frequency": 0.1238568588469185,
      "rolling_250_frequency": 0.124,
      "gap_rhythm_score": 0.13592544891984348,
      "sgd_log_probability": 0.4973256879604918,
      "gaussian_nb_probability": 0.1595851950916943,
      "pro_ensemble_score": 0.5620408163265306
    },
    {
      "number": 4,
      "rank": 21,
      "current_gap": 1,
      "average_gap": 7.865987460815047,
      "median_gap": 6.0,
      "total_hits": 1277,
      "prior_frequency": 0.12693836978131212,
      "rolling_250_frequency": 0.104,
      "gap_rhythm_score": 0.09589436943396501,
      "sgd_log_probability": 0.4980498268252716,
      "gaussian_nb_probability": 0.1631858710348229,
      "pro_ensemble_score": 0.5285714285714286
    },
    {
      "number": 24,
      "rank": 22,
      "current_gap": 15,
      "average_gap": 8.103309120258272,
      "median_gap": 6.0,
      "total_hits": 1240,
      "prior_frequency": 0.12326043737574553,
      "rolling_250_frequency": 0.144,
      "gap_rhythm_score": 0.22994705629970758,
      "sgd_log_probability": 0.4660457961899716,
      "gaussian_nb_probability": 0.1495843706124583,
      "pro_ensemble_score": 0.5183673469387755
    },
    {
      "number": 45,
      "rank": 23,
      "current_gap": 11,
      "average_gap": 8.106709781729991,
      "median_gap": 6.0,
      "total_hits": 1238,
      "prior_frequency": 0.12306163021868788,
      "rolling_250_frequency": 0.1,
      "gap_rhythm_score": 0.17198922759506116,
      "sgd_log_probability": 0.5007532568292817,
      "gaussian_nb_probability": 0.1554361726356935,
      "pro_ensemble_score": 0.5175510204081633
    },
    {
      "number": 36,
      "rank": 24,
      "current_gap": 12,
      "average_gap": 8.224590163934426,
      "median_gap": 6.0,
      "total_hits": 1221,
      "prior_frequency": 0.12137176938369781,
      "rolling_250_frequency": 0.148,
      "gap_rhythm_score": 0.2035177277257325,
      "sgd_log_probability": 0.48129014548036014,
      "gaussian_nb_probability": 0.1534211493248793,
      "pro_ensemble_score": 0.5146938775510204
    },
    {
      "number": 2,
      "rank": 25,
      "current_gap": 1,
      "average_gap": 8.229950900163667,
      "median_gap": 6.0,
      "total_hits": 1223,
      "prior_frequency": 0.12157057654075547,
      "rolling_250_frequency": 0.152,
      "gap_rhythm_score": 0.09525965927546319,
      "sgd_log_probability": 0.5011706522430308,
      "gaussian_nb_probability": 0.15434379898392275,
      "pro_ensemble_score": 0.5118367346938776
    },
    {
      "number": 15,
      "rank": 26,
      "current_gap": 6,
      "average_gap": 8.239344262295083,
      "median_gap": 6.0,
      "total_hits": 1221,
      "prior_frequency": 0.12137176938369781,
      "rolling_250_frequency": 0.128,
      "gap_rhythm_score": 0.11836138479904497,
      "sgd_log_probability": 0.49250036904309125,
      "gaussian_nb_probability": 0.1612862612249573,
      "pro_ensemble_score": 0.49918367346938775
    },
    {
      "number": 47,
      "rank": 27,
      "current_gap": 2,
      "average_gap": 8.284184514003295,
      "median_gap": 6.0,
      "total_hits": 1215,
      "prior_frequency": 0.12077534791252485,
      "rolling_250_frequency": 0.104,
      "gap_rhythm_score": 0.06888931755659408,
      "sgd_log_probability": 0.5213263039102382,
      "gaussian_nb_probability": 0.16069236545907228,
      "pro_ensemble_score": 0.48857142857142855
    },
    {
      "number": 34,
      "rank": 28,
      "current_gap": 32,
      "average_gap": 7.765116279069767,
      "median_gap": 5.0,
      "total_hits": 1291,
      "prior_frequency": 0.1283300198807157,
      "rolling_250_frequency": 0.128,
      "gap_rhythm_score": 0.4260705086836637,
      "sgd_log_probability": 0.4377451782243094,
      "gaussian_nb_probability": 0.12164631187060662,
      "pro_ensemble_score": 0.4844897959183673
    },
    {
      "number": 13,
      "rank": 29,
      "current_gap": 3,
      "average_gap": 8.2833607907743,
      "median_gap": 6.0,
      "total_hits": 1215,
      "prior_frequency": 0.12077534791252485,
      "rolling_250_frequency": 0.144,
      "gap_rhythm_score": 0.11757556085918854,
      "sgd_log_probability": 0.4968000805557346,
      "gaussian_nb_probability": 0.1538226708198459,
      "pro_ensemble_score": 0.4722448979591837
    },
    {
      "number": 9,
      "rank": 30,
      "current_gap": 7,
      "average_gap": 8.028776978417266,
      "median_gap": 6.0,
      "total_hits": 1252,
      "prior_frequency": 0.12445328031809146,
      "rolling_250_frequency": 0.092,
      "gap_rhythm_score": 0.1456536978489225,
      "sgd_log_probability": 0.48603520692952223,
      "gaussian_nb_probability": 0.15897170938824828,
      "pro_ensemble_score": 0.4644897959183673
    },
    {
      "number": 16,
      "rank": 31,
      "current_gap": 3,
      "average_gap": 8.364696086594504,
      "median_gap": 6.0,
      "total_hits": 1202,
      "prior_frequency": 0.1194831013916501,
      "rolling_250_frequency": 0.136,
      "gap_rhythm_score": 0.09802060919769064,
      "sgd_log_probability": 0.4961859520466217,
      "gaussian_nb_probability": 0.1608030808658893,
      "pro_ensemble_score": 0.4530612244897959
    },
    {
      "number": 21,
      "rank": 32,
      "current_gap": 22,
      "average_gap": 7.791149068322981,
      "median_gap": 5.5,
      "total_hits": 1289,
      "prior_frequency": 0.12813121272365804,
      "rolling_250_frequency": 0.096,
      "gap_rhythm_score": 0.33867038860502896,
      "sgd_log_probability": 0.4529027814379807,
      "gaussian_nb_probability": 0.1429719287165433,
      "pro_ensemble_score": 0.4326530612244898
    },
    {
      "number": 23,
      "rank": 33,
      "current_gap": 15,
      "average_gap": 8.595034246575343,
      "median_gap": 6.0,
      "total_hits": 1169,
      "prior_frequency": 0.1162027833001988,
      "rolling_250_frequency": 0.172,
      "gap_rhythm_score": 0.23618852475346153,
      "sgd_log_probability": 0.46541106371539315,
      "gaussian_nb_probability": 0.13784106773274948,
      "pro_ensemble_score": 0.43224489795918364
    },
    {
      "number": 18,
      "rank": 34,
      "current_gap": 18,
      "average_gap": 8.4,
      "median_gap": 6.0,
      "total_hits": 1196,
      "prior_frequency": 0.11888667992047713,
      "rolling_250_frequency": 0.148,
      "gap_rhythm_score": 0.2601057142857143,
      "sgd_log_probability": 0.44990223645498606,
      "gaussian_nb_probability": 0.14169096026378203,
      "pro_ensemble_score": 0.4114285714285714
    },
    {
      "number": 1,
      "rank": 35,
      "current_gap": 5,
      "average_gap": 8.0368,
      "median_gap": 6.0,
      "total_hits": 1251,
      "prior_frequency": 0.12435387673956262,
      "rolling_250_frequency": 0.088,
      "gap_rhythm_score": 0.13314914423108554,
      "sgd_log_probability": 0.4887283896991146,
      "gaussian_nb_probability": 0.15377071858865055,
      "pro_ensemble_score": 0.4073469387755102
    },
    {
      "number": 14,
      "rank": 36,
      "current_gap": 5,
      "average_gap": 8.334162520729684,
      "median_gap": 6.0,
      "total_hits": 1207,
      "prior_frequency": 0.11998011928429424,
      "rolling_250_frequency": 0.112,
      "gap_rhythm_score": 0.1073040400623487,
      "sgd_log_probability": 0.4940379952988749,
      "gaussian_nb_probability": 0.16119468532438466,
      "pro_ensemble_score": 0.3983673469387755
    },
    {
      "number": 27,
      "rank": 37,
      "current_gap": 15,
      "average_gap": 8.38313856427379,
      "median_gap": 6.0,
      "total_hits": 1199,
      "prior_frequency": 0.11918489065606362,
      "rolling_250_frequency": 0.12,
      "gap_rhythm_score": 0.21080946330777656,
      "sgd_log_probability": 0.47235438856039325,
      "gaussian_nb_probability": 0.14956697218789575,
      "pro_ensemble_score": 0.39632653061224493
    },
    {
      "number": 5,
      "rank": 38,
      "current_gap": 2,
      "average_gap": 8.237079573420838,
      "median_gap": 6.0,
      "total_hits": 1220,
      "prior_frequency": 0.12127236580516898,
      "rolling_250_frequency": 0.108,
      "gap_rhythm_score": 0.0760100647345882,
      "sgd_log_probability": 0.49609294421247907,
      "gaussian_nb_probability": 0.16259483698956206,
      "pro_ensemble_score": 0.3955102040816326
    },
    {
      "number": 12,
      "rank": 39,
      "current_gap": 25,
      "average_gap": 8.040865384615385,
      "median_gap": 6.0,
      "total_hits": 1249,
      "prior_frequency": 0.12415506958250497,
      "rolling_250_frequency": 0.12,
      "gap_rhythm_score": 0.33716300944042804,
      "sgd_log_probability": 0.4315797443366058,
      "gaussian_nb_probability": 0.1282129313103545,
      "pro_ensemble_score": 0.39061224489795926
    },
    {
      "number": 19,
      "rank": 40,
      "current_gap": 3,
      "average_gap": 8.454163162321278,
      "median_gap": 6.0,
      "total_hits": 1190,
      "prior_frequency": 0.11829025844930417,
      "rolling_250_frequency": 0.12,
      "gap_rhythm_score": 0.09513360923199364,
      "sgd_log_probability": 0.5003493195679061,
      "gaussian_nb_probability": 0.1589055497244722,
      "pro_ensemble_score": 0.3873469387755102
    },
    {
      "number": 31,
      "rank": 41,
      "current_gap": 14,
      "average_gap": 8.528013582342954,
      "median_gap": 6.0,
      "total_hits": 1179,
      "prior_frequency": 0.11719681908548708,
      "rolling_250_frequency": 0.128,
      "gap_rhythm_score": 0.1952791970270091,
      "sgd_log_probability": 0.47845793649675333,
      "gaussian_nb_probability": 0.14569802836590742,
      "pro_ensemble_score": 0.3853061224489796
    },
    {
      "number": 20,
      "rank": 42,
      "current_gap": 16,
      "average_gap": 8.222131147540983,
      "median_gap": 6.0,
      "total_hits": 1221,
      "prior_frequency": 0.12137176938369781,
      "rolling_250_frequency": 0.108,
      "gap_rhythm_score": 0.22517590336623133,
      "sgd_log_probability": 0.45950935869566745,
      "gaussian_nb_probability": 0.1503037824354541,
      "pro_ensemble_score": 0.38244897959183677
    },
    {
      "number": 10,
      "rank": 43,
      "current_gap": 6,
      "average_gap": 8.375833333333333,
      "median_gap": 6.0,
      "total_hits": 1201,
      "prior_frequency": 0.11938369781312128,
      "rolling_250_frequency": 0.124,
      "gap_rhythm_score": 0.11363925181573974,
      "sgd_log_probability": 0.4833514811460447,
      "gaussian_nb_probability": 0.15931613272784476,
      "pro_ensemble_score": 0.37918367346938775
    },
    {
      "number": 3,
      "rank": 44,
      "current_gap": 12,
      "average_gap": 8.495342929720575,
      "median_gap": 6.0,
      "total_hits": 1182,
      "prior_frequency": 0.11749502982107356,
      "rolling_250_frequency": 0.108,
      "gap_rhythm_score": 0.18169169939200638,
      "sgd_log_probability": 0.45688773248967085,
      "gaussian_nb_probability": 0.15483021823550122,
      "pro_ensemble_score": 0.3310204081632653
    },
    {
      "number": 7,
      "rank": 45,
      "current_gap": 5,
      "average_gap": 8.280889621087315,
      "median_gap": 6.0,
      "total_hits": 1215,
      "prior_frequency": 0.12077534791252485,
      "rolling_250_frequency": 0.088,
      "gap_rhythm_score": 0.11021386053914255,
      "sgd_log_probability": 0.49041455693117314,
      "gaussian_nb_probability": 0.1556321868721971,
      "pro_ensemble_score": 0.3195918367346939
    },
    {
      "number": 25,
      "rank": 46,
      "current_gap": 27,
      "average_gap": 8.09765940274415,
      "median_gap": 6.0,
      "total_hits": 1240,
      "prior_frequency": 0.12326043737574553,
      "rolling_250_frequency": 0.084,
      "gap_rhythm_score": 0.32766790923005734,
      "sgd_log_probability": 0.43806047764981254,
      "gaussian_nb_probability": 0.1104309496942254,
      "pro_ensemble_score": 0.3183673469387755
    },
    {
      "number": 41,
      "rank": 47,
      "current_gap": 21,
      "average_gap": 8.559726962457338,
      "median_gap": 6.0,
      "total_hits": 1173,
      "prior_frequency": 0.11660039761431412,
      "rolling_250_frequency": 0.1,
      "gap_rhythm_score": 0.26114736842105263,
      "sgd_log_probability": 0.46256735292926093,
      "gaussian_nb_probability": 0.12885279132135233,
      "pro_ensemble_score": 0.3004081632653061
    },
    {
      "number": 32,
      "rank": 48,
      "current_gap": 13,
      "average_gap": 8.349127182044887,
      "median_gap": 6.0,
      "total_hits": 1204,
      "prior_frequency": 0.11968190854870775,
      "rolling_250_frequency": 0.076,
      "gap_rhythm_score": 0.16924348864994027,
      "sgd_log_probability": 0.4821352419226983,
      "gaussian_nb_probability": 0.1380702396074657,
      "pro_ensemble_score": 0.29061224489795917
    },
    {
      "number": 40,
      "rank": 49,
      "current_gap": 4,
      "average_gap": 8.63175965665236,
      "median_gap": 6.0,
      "total_hits": 1166,
      "prior_frequency": 0.11590457256461233,
      "rolling_250_frequency": 0.08,
      "gap_rhythm_score": 0.08458315035799523,
      "sgd_log_probability": 0.5031352401155496,
      "gaussian_nb_probability": 0.14831609974935914,
      "pro_ensemble_score": 0.2816326530612245
    }
  ],
  "warning": "Lottery draws are random. This model ranks historical/statistical signals; it is not a guarantee and does not prove future winning numbers."
}