{
  "module": "pattern_balance_engine",
  "version": "v54",
  "user_facing_name_bg": "Баланс на комбинациите",
  "purpose_bg": "Оценява структурния баланс на една или повече 6/49 комбинации: четни/нечетни, ниски/високи, сума, диапазони, поредици, разстояния и крайни цифри.",
  "not_a_prediction_bg": "Модулът не предсказва печеливши числа и не гарантира печалба. Той измерва само структурата на избраните комбинации.",
  "metrics": [
    "odd_even_distribution",
    "low_high_distribution",
    "sum",
    "sum_band",
    "range_distribution",
    "final_digit_distribution",
    "gaps",
    "minimum_gap",
    "maximum_gap",
    "average_gap",
    "longest_consecutive_run",
    "consecutive_pairs",
    "pattern_score"
  ],
  "score_bands": {
    "80_100": "Отличен баланс",
    "65_79": "Добър баланс",
    "45_64": "Среден баланс",
    "0_44": "Небалансирана структура"
  }
}